{
  "run_nums": [
    204774,
    204775,
    204776,
    204777,
    204778,
    204779,
    204780,
    204781,
    204782,
    204783,
    204784,
    204785,
    204786,
    204787,
    204788,
    204789,
    204790,
    204791,
    204792,
    204793,
    204794,
    204795,
    204796,
    204797,
    204798,
    204799,
    204800,
    204801,
    204802,
    204803,
    204804,
    204805,
    204806,
    204807,
    204808,
    204809,
    204810,
    204811,
    204812,
    204813,
    204814,
    204815,
    204816,
    204817,
    204818,
    204819,
    204820,
    204821,
    204822,
    204823,
    204824,
    204825,
    204826,
    204827,
    204828,
    204829,
    204830,
    204831,
    204832,
    204833,
    204834,
    204835,
    204836,
    204837,
    204838,
    204839,
    204840,
    204841,
    204842,
    204843,
    204844,
    204845,
    204846,
    204847,
    204848,
    204849,
    204850,
    204851,
    204852,
    204853,
    204854,
    204855,
    204856,
    204857,
    204858,
    204859,
    204860,
    204861,
    204862,
    204863,
    204864,
    204865,
    204866,
    204867
  ],
  "settings": {
    "screen": {
      "width": 1280,
      "height": 832
    },
    "display_mode": 2,
    "draw": false,
    "drawSometimes": true,
    "drawAmnt": 500,
    "population_cap": 0.5,
    "enviormentChangeRate": 0.64,
    "ph_effect": {
      "scale": 2.0,
      "divisor": 2.0
    },
    "temp_effect": {
      "scale": 2.0,
      "divisor": 4.0
    },
    "reproduction_debuf_min": 0.001,
    "quan": 2.0,
    "immune_system_quan_factor": 0.13,
    "num_tries_hub": 69,
    "simulations": {
      "count": 94
    },
    "master_graph": {
      "dot_alpha": 50,
      "dot_radius": 3
    },
    "hub": {
      "start_rate": 0.5,
      "end_rate": 2.5,
      "step": 0.01,
      "species_threshold": 20000,
      "max_masters": 241
    },
    "stop_conditions": {
      "runtime_enabled": false,
      "max_runtime_hours": 0.0,
      "frames_enabled": false,
      "max_frames": 0,
      "species_enabled": true,
      "max_species": 20000,
      "datetime_enabled": false,
      "stop_at_datetime": ""
    }
  },
  "updated_at": 1771972892.0506454
}