{
  "run_nums": [
    209568,
    209569,
    209570,
    209571,
    209572,
    209573,
    209574,
    209575,
    209576,
    209577,
    209578,
    209579,
    209580,
    209581,
    209582,
    209583,
    209584,
    209585,
    209586,
    209587,
    209588,
    209589,
    209590,
    209591,
    209592,
    209593,
    209594,
    209595,
    209596,
    209597,
    209598,
    209599,
    209600,
    209601,
    209602,
    209603,
    209604,
    209605,
    209606,
    209607,
    209608,
    209609,
    209610,
    209611,
    209612,
    209613,
    209614,
    209615,
    209616,
    209617,
    209618,
    209619,
    209620,
    209621,
    209622,
    209623,
    209624,
    209625,
    209626,
    209627,
    209628,
    209629,
    209630,
    209631,
    209632,
    209633,
    209634,
    209635,
    209636,
    209637,
    209638,
    209639,
    209640,
    209641,
    209642,
    209643,
    209644,
    209645,
    209646,
    209647,
    209648,
    209649,
    209650,
    209651,
    209652,
    209653,
    209654,
    209655,
    209656,
    209657,
    209658,
    209659,
    209660,
    209661
  ],
  "settings": {
    "screen": {
      "width": 1280,
      "height": 832
    },
    "display_mode": 2,
    "draw": false,
    "drawSometimes": true,
    "drawAmnt": 500,
    "population_cap": 0.5,
    "enviormentChangeRate": 1.15,
    "ph_effect": {
      "scale": 2.0,
      "divisor": 2.0
    },
    "temp_effect": {
      "scale": 2.0,
      "divisor": 4.0
    },
    "reproduction_debuf_min": 0.001,
    "quan": 2.0,
    "immune_system_quan_factor": 0.13,
    "num_tries_hub": 69,
    "simulations": {
      "count": 94
    },
    "master_graph": {
      "dot_alpha": 50,
      "dot_radius": 3
    },
    "hub": {
      "start_rate": 0.5,
      "end_rate": 2.5,
      "step": 0.01,
      "species_threshold": 20000,
      "max_masters": 241
    },
    "stop_conditions": {
      "runtime_enabled": false,
      "max_runtime_hours": 0.0,
      "frames_enabled": false,
      "max_frames": 0,
      "species_enabled": true,
      "max_species": 20000,
      "datetime_enabled": false,
      "stop_at_datetime": ""
    }
  },
  "updated_at": 1771995377.9639676
}