{
  "hub_index": 65,
  "created_at": 1771907533.6039498,
  "start_rate": 0.5,
  "end_rate": 2.5,
  "step": 0.01,
  "species_threshold": 8000,
  "max_masters": 241,
  "rates": [
    0.5,
    0.51,
    0.52,
    0.53,
    0.54,
    0.55,
    0.56,
    0.57,
    0.58,
    0.59,
    0.6,
    0.61,
    0.62,
    0.63,
    0.64,
    0.65,
    0.66,
    0.67,
    0.68,
    0.69,
    0.7,
    0.71,
    0.72,
    0.73,
    0.74,
    0.75,
    0.76,
    0.77,
    0.78,
    0.79,
    0.8,
    0.81,
    0.82,
    0.83,
    0.84,
    0.85,
    0.86,
    0.87,
    0.88,
    0.89,
    0.9,
    0.91,
    0.92,
    0.93,
    0.94,
    0.95,
    0.96,
    0.97,
    0.98,
    0.99,
    1.0,
    1.01,
    1.02,
    1.03,
    1.04,
    1.05,
    1.06,
    1.07,
    1.08,
    1.09,
    1.1,
    1.11,
    1.12,
    1.13,
    1.14,
    1.15,
    1.16,
    1.17,
    1.18,
    1.19,
    1.2,
    1.21,
    1.22,
    1.23,
    1.24,
    1.25,
    1.26,
    1.27,
    1.28,
    1.29,
    1.3,
    1.31,
    1.32,
    1.33,
    1.34,
    1.35,
    1.36,
    1.37,
    1.38,
    1.39,
    1.4,
    1.41,
    1.42,
    1.43,
    1.44,
    1.45,
    1.46,
    1.47,
    1.48,
    1.49,
    1.5,
    1.51,
    1.52,
    1.53,
    1.54,
    1.55,
    1.56,
    1.57,
    1.58,
    1.59,
    1.6,
    1.61,
    1.62,
    1.63,
    1.64,
    1.65,
    1.66,
    1.67,
    1.68,
    1.69,
    1.7,
    1.71,
    1.72,
    1.73,
    1.74,
    1.75,
    1.76,
    1.77,
    1.78,
    1.79,
    1.8,
    1.81,
    1.82,
    1.83,
    1.84,
    1.85,
    1.86,
    1.87,
    1.88,
    1.89,
    1.9,
    1.91,
    1.92,
    1.93,
    1.94,
    1.95,
    1.96,
    1.97,
    1.98,
    1.99,
    2.0,
    2.01,
    2.02,
    2.03,
    2.04,
    2.05,
    2.06,
    2.07,
    2.08,
    2.09,
    2.1,
    2.11,
    2.12,
    2.13,
    2.14,
    2.15,
    2.16,
    2.17,
    2.18,
    2.19,
    2.2,
    2.21,
    2.22,
    2.23,
    2.24,
    2.25,
    2.26,
    2.27,
    2.28,
    2.29,
    2.3,
    2.31,
    2.32,
    2.33,
    2.34,
    2.35,
    2.36,
    2.37,
    2.38,
    2.39,
    2.4,
    2.41,
    2.42,
    2.43,
    2.44,
    2.45,
    2.46,
    2.47,
    2.48,
    2.49,
    2.5
  ],
  "planned_master_ids": [
    7900,
    7901,
    7902,
    7903,
    7904,
    7905,
    7906,
    7907,
    7908,
    7909,
    7910,
    7911,
    7912,
    7913,
    7914,
    7915,
    7916,
    7917,
    7918,
    7919,
    7920,
    7921,
    7922,
    7923,
    7924,
    7925,
    7926,
    7927,
    7928,
    7929,
    7930,
    7931,
    7932,
    7933,
    7934,
    7935,
    7936,
    7937,
    7938,
    7939,
    7940,
    7941,
    7942,
    7943,
    7944,
    7945,
    7946,
    7947,
    7948,
    7949,
    7950,
    7951,
    7952,
    7953,
    7954,
    7955,
    7956,
    7957,
    7958,
    7959,
    7960,
    7961,
    7962,
    7963,
    7964,
    7965,
    7966,
    7967,
    7968,
    7969,
    7970,
    7971,
    7972,
    7973,
    7974,
    7975,
    7976,
    7977,
    7978,
    7979,
    7980,
    7981,
    7982,
    7983,
    7984,
    7985,
    7986,
    7987,
    7988,
    7989,
    7990,
    7991,
    7992,
    7993,
    7994,
    7995,
    7996,
    7997,
    7998,
    7999,
    8000,
    8001,
    8002,
    8003,
    8004,
    8005,
    8006,
    8007,
    8008,
    8009,
    8010,
    8011,
    8012,
    8013,
    8014,
    8015,
    8016,
    8017,
    8018,
    8019,
    8020,
    8021,
    8022,
    8023,
    8024,
    8025,
    8026,
    8027,
    8028,
    8029,
    8030,
    8031,
    8032,
    8033,
    8034,
    8035,
    8036,
    8037,
    8038,
    8039,
    8040,
    8041,
    8042,
    8043,
    8044,
    8045,
    8046,
    8047,
    8048,
    8049,
    8050,
    8051,
    8052,
    8053,
    8054,
    8055,
    8056,
    8057,
    8058,
    8059,
    8060,
    8061,
    8062,
    8063,
    8064,
    8065,
    8066,
    8067,
    8068,
    8069,
    8070,
    8071,
    8072,
    8073,
    8074,
    8075,
    8076,
    8077,
    8078,
    8079,
    8080,
    8081,
    8082,
    8083,
    8084,
    8085,
    8086,
    8087,
    8088,
    8089,
    8090,
    8091,
    8092,
    8093,
    8094,
    8095,
    8096,
    8097,
    8098,
    8099,
    8100
  ],
  "planned_master_range": "7900-8100",
  "steps": [
    {
      "step_index": 0,
      "env_rate": 0.5,
      "env_dir": "results/hub/hub_65/env_0p50",
      "planned_master_run_num": 7900,
      "returncode": 0,
      "finished_at": 1771907675.6687503,
      "status": "ok",
      "master_dir": "results/hub/hub_65/env_0p50/master_7900",
      "master_run_num": 7900,
      "run_nums": [
        135476,
        135477,
        135478,
        135479,
        135480,
        135481,
        135482,
        135483,
        135484,
        135485,
        135486,
        135487,
        135488,
        135489,
        135490,
        135491,
        135492,
        135493,
        135494,
        135495,
        135496,
        135497,
        135498,
        135499,
        135500,
        135501,
        135502,
        135503,
        135504,
        135505
      ],
      "max_species": 288.0,
      "total_species": 8101.0,
      "max_frames": 308850.0,
      "apex_evolution_rate": 0.161,
      "apex_fitness": 1191.7341725721233,
      "fit": {
        "apex_x": 0.161,
        "apex_y": 1191.7341725721233,
        "apex_point_y": 2039.7272727272727,
        "sigma_left": 0.13056246493556578,
        "sigma_right": 0.08880485939091662,
        "shape_power": 1.4,
        "r2": 0.6741612204176919,
        "equation": "y=1191.73*exp(-(|x-0.161|^1.4)/(2*0.130562^1.4)) for x<=0.161; y=1191.73*exp(-(|x-0.161|^1.4)/(2*0.0888049^1.4)) for x>0.161"
      },
      "point_count": 351
    },
    {
      "step_index": 1,
      "env_rate": 0.51,
      "env_dir": "results/hub/hub_65/env_0p51",
      "planned_master_run_num": 7901,
      "returncode": 0,
      "finished_at": 1771907825.9422941,
      "status": "ok",
      "master_dir": "results/hub/hub_65/env_0p51/master_7901",
      "master_run_num": 7901,
      "run_nums": [
        135506,
        135507,
        135508,
        135509,
        135510,
        135511,
        135512,
        135513,
        135514,
        135515,
        135516,
        135517,
        135518,
        135519,
        135520,
        135521,
        135522,
        135523,
        135524,
        135525,
        135526,
        135527,
        135528,
        135529,
        135530,
        135531,
        135532,
        135533,
        135534,
        135535
      ],
      "max_species": 280.0,
      "total_species": 8057.0,
      "max_frames": 320100.0,
      "apex_evolution_rate": 0.175,
      "apex_fitness": 760.1946817099385,
      "fit": {
        "apex_x": 0.175,
        "apex_y": 760.1946817099385,
        "apex_point_y": 1492.3333333333333,
        "sigma_left": 0.2646811599887121,
        "sigma_right": 0.1106477419494771,
        "shape_power": 1.5,
        "r2": 0.5458576930787715,
        "equation": "y=760.195*exp(-(|x-0.175|^1.5)/(2*0.264681^1.5)) for x<=0.175; y=760.195*exp(-(|x-0.175|^1.5)/(2*0.110648^1.5)) for x>0.175"
      },
      "point_count": 351
    },
    {
      "step_index": 2,
      "env_rate": 0.52,
      "env_dir": "results/hub/hub_65/env_0p52",
      "planned_master_run_num": 7902,
      "returncode": 0,
      "finished_at": 1771907969.239906,
      "status": "ok",
      "master_dir": "results/hub/hub_65/env_0p52/master_7902",
      "master_run_num": 7902,
      "run_nums": [
        135536,
        135537,
        135538,
        135539,
        135540,
        135541,
        135542,
        135543,
        135544,
        135545,
        135546,
        135547,
        135548,
        135549,
        135550,
        135551,
        135552,
        135553,
        135554,
        135555,
        135556,
        135557,
        135558,
        135559,
        135560,
        135561,
        135562,
        135563,
        135564,
        135565
      ],
      "max_species": 283.0,
      "total_species": 8051.0,
      "max_frames": 327100.0,
      "apex_evolution_rate": 0.163,
      "apex_fitness": 780.5859582717367,
      "fit": {
        "apex_x": 0.163,
        "apex_y": 780.5859582717367,
        "apex_point_y": 1567.3809523809523,
        "sigma_left": 0.15907835636416817,
        "sigma_right": 0.12516094393205643,
        "shape_power": 1.8,
        "r2": 0.5027091929975557,
        "equation": "y=780.586*exp(-(|x-0.163|^1.8)/(2*0.159078^1.8)) for x<=0.163; y=780.586*exp(-(|x-0.163|^1.8)/(2*0.125161^1.8)) for x>0.163"
      },
      "point_count": 351
    },
    {
      "step_index": 3,
      "env_rate": 0.53,
      "env_dir": "results/hub/hub_65/env_0p53",
      "planned_master_run_num": 7903,
      "returncode": 0,
      "finished_at": 1771908114.4591925,
      "status": "ok",
      "master_dir": "results/hub/hub_65/env_0p53/master_7903",
      "master_run_num": 7903,
      "run_nums": [
        135566,
        135567,
        135568,
        135569,
        135570,
        135571,
        135572,
        135573,
        135574,
        135575,
        135576,
        135577,
        135578,
        135579,
        135580,
        135581,
        135582,
        135583,
        135584,
        135585,
        135586,
        135587,
        135588,
        135589,
        135590,
        135591,
        135592,
        135593,
        135594,
        135595
      ],
      "max_species": 281.0,
      "total_species": 8078.0,
      "max_frames": 319650.0,
      "apex_evolution_rate": 0.206,
      "apex_fitness": 943.934253436318,
      "fit": {
        "apex_x": 0.206,
        "apex_y": 943.934253436318,
        "apex_point_y": 1675.3809523809523,
        "sigma_left": 0.17784770188963617,
        "sigma_right": 0.03499410884134101,
        "shape_power": 0.6,
        "r2": 0.5882179782814556,
        "equation": "y=943.934*exp(-(|x-0.206|^0.6)/(2*0.177848^0.6)) for x<=0.206; y=943.934*exp(-(|x-0.206|^0.6)/(2*0.0349941^0.6)) for x>0.206"
      },
      "point_count": 351
    },
    {
      "step_index": 4,
      "env_rate": 0.54,
      "env_dir": "results/hub/hub_65/env_0p54",
      "planned_master_run_num": 7904,
      "returncode": 0,
      "finished_at": 1771908258.545427,
      "status": "ok",
      "master_dir": "results/hub/hub_65/env_0p54/master_7904",
      "master_run_num": 7904,
      "run_nums": [
        135596,
        135597,
        135598,
        135599,
        135600,
        135601,
        135602,
        135603,
        135604,
        135605,
        135606,
        135607,
        135608,
        135609,
        135610,
        135611,
        135612,
        135613,
        135614,
        135615,
        135616,
        135617,
        135618,
        135619,
        135620,
        135621,
        135622,
        135623,
        135624,
        135625
      ],
      "max_species": 283.0,
      "total_species": 8067.0,
      "max_frames": 321600.0,
      "apex_evolution_rate": 0.195,
      "apex_fitness": 977.6672935243535,
      "fit": {
        "apex_x": 0.195,
        "apex_y": 977.6672935243535,
        "apex_point_y": 1442.7222222222222,
        "sigma_left": 0.12600491786452436,
        "sigma_right": 0.03528495074660862,
        "shape_power": 0.6,
        "r2": 0.5885925225819464,
        "equation": "y=977.667*exp(-(|x-0.195|^0.6)/(2*0.126005^0.6)) for x<=0.195; y=977.667*exp(-(|x-0.195|^0.6)/(2*0.035285^0.6)) for x>0.195"
      },
      "point_count": 351
    },
    {
      "step_index": 5,
      "env_rate": 0.55,
      "env_dir": "results/hub/hub_65/env_0p55",
      "planned_master_run_num": 7905,
      "returncode": 0,
      "finished_at": 1771908403.9130774,
      "status": "ok",
      "master_dir": "results/hub/hub_65/env_0p55/master_7905",
      "master_run_num": 7905,
      "run_nums": [
        135626,
        135627,
        135628,
        135629,
        135630,
        135631,
        135632,
        135633,
        135634,
        135635,
        135636,
        135637,
        135638,
        135639,
        135640,
        135641,
        135642,
        135643,
        135644,
        135645,
        135646,
        135647,
        135648,
        135649,
        135650,
        135651,
        135652,
        135653,
        135654,
        135655
      ],
      "max_species": 284.0,
      "total_species": 8055.0,
      "max_frames": 325900.0,
      "apex_evolution_rate": 0.168,
      "apex_fitness": 819.228083537156,
      "fit": {
        "apex_x": 0.168,
        "apex_y": 819.228083537156,
        "apex_point_y": 1577.0714285714287,
        "sigma_left": 0.1407067685060999,
        "sigma_right": 0.10009595276706836,
        "shape_power": 1.3,
        "r2": 0.49650756889269165,
        "equation": "y=819.228*exp(-(|x-0.168|^1.3)/(2*0.140707^1.3)) for x<=0.168; y=819.228*exp(-(|x-0.168|^1.3)/(2*0.100096^1.3)) for x>0.168"
      },
      "point_count": 351
    },
    {
      "step_index": 6,
      "env_rate": 0.56,
      "env_dir": "results/hub/hub_65/env_0p56",
      "planned_master_run_num": 7906,
      "returncode": 0,
      "finished_at": 1771908549.2138486,
      "status": "ok",
      "master_dir": "results/hub/hub_65/env_0p56/master_7906",
      "master_run_num": 7906,
      "run_nums": [
        135656,
        135657,
        135658,
        135659,
        135660,
        135661,
        135662,
        135663,
        135664,
        135665,
        135666,
        135667,
        135668,
        135669,
        135670,
        135671,
        135672,
        135673,
        135674,
        135675,
        135676,
        135677,
        135678,
        135679,
        135680,
        135681,
        135682,
        135683,
        135684,
        135685
      ],
      "max_species": 284.0,
      "total_species": 8044.0,
      "max_frames": 325150.0,
      "apex_evolution_rate": 0.159,
      "apex_fitness": 738.5641028063034,
      "fit": {
        "apex_x": 0.159,
        "apex_y": 738.5641028063034,
        "apex_point_y": 1418.2777777777778,
        "sigma_left": 0.18151271415081421,
        "sigma_right": 0.13923748534656294,
        "shape_power": 1.9,
        "r2": 0.48727837128010254,
        "equation": "y=738.564*exp(-(|x-0.159|^1.9)/(2*0.181513^1.9)) for x<=0.159; y=738.564*exp(-(|x-0.159|^1.9)/(2*0.139237^1.9)) for x>0.159"
      },
      "point_count": 351
    }
  ],
  "status": "running"
}